{"generated_at":"2026-02-26T18:55:08.591776Z","state":"MA","state_name":"Massachusetts","gov_term_years":4,"gov_term_limit":"None","pres_2024_margin":"D+25.2","next_regular_election":2026,"current_governor":{"name":"Maura Healey","party":"D","since":"2023-01-05","start_reason":"elected"},"timeline":[{"name":"Maura Healey","party":"D","start":"2023-01-05","end":null,"start_reason":"elected","end_reason":null,"election_year":null,"margin":null},{"name":"Charlie Baker","party":"R","start":"2015-01-08","end":"2023-01-05","start_reason":"elected","end_reason":"term_expired","election_year":2014,"margin":null},{"name":"Deval Patrick","party":"D","start":"2007-01-04","end":"2015-01-08","start_reason":"elected","end_reason":"term_expired","election_year":2006,"margin":null},{"name":"Mitt Romney","party":"R","start":"2003-01-02","end":"2007-01-04","start_reason":"elected","end_reason":"term_expired","election_year":2002,"margin":null},{"name":"Jane Swift","party":"R","start":"2001-04-10","end":"2003-01-02","start_reason":"succeeded","end_reason":"term_expired","election_year":null,"margin":null},{"name":"Paul Cellucci","party":"R","start":"1997-07-29","end":"2001-04-10","start_reason":"elected","end_reason":"resigned","election_year":null,"margin":null},{"name":"Bill Weld","party":"R","start":"1991-01-03","end":"1997-07-29","start_reason":"elected","end_reason":"resigned","election_year":1990,"margin":null},{"name":"Michael Dukakis","party":"D","start":"1983-01-06","end":"1991-01-03","start_reason":"elected","end_reason":"term_expired","election_year":1982,"margin":null},{"name":"Edward J. King","party":"D","start":"1979-01-04","end":"1983-01-06","start_reason":"elected","end_reason":"lost_election","election_year":1978,"margin":null},{"name":"Michael Dukakis","party":"D","start":"1975-01-02","end":"1979-01-04","start_reason":"elected","end_reason":"lost_election","election_year":1974,"margin":null},{"name":"Francis Sargent","party":"R","start":"1969-01-22","end":"1975-01-02","start_reason":"elected","end_reason":"lost_election","election_year":null,"margin":null},{"name":"John A. Volpe","party":"R","start":"1965-01-07","end":"1969-01-22","start_reason":"elected","end_reason":"resigned","election_year":1964,"margin":null},{"name":"Endicott Peabody","party":"D","start":"1963-01-03","end":"1965-01-07","start_reason":"elected","end_reason":"lost_election","election_year":1962,"margin":null},{"name":"John A. Volpe","party":"R","start":"1961-01-05","end":"1963-01-03","start_reason":"elected","end_reason":"lost_election","election_year":1960,"margin":null},{"name":"Foster Furcolo","party":"D","start":"1957-01-03","end":"1961-01-05","start_reason":"elected","end_reason":"term_expired","election_year":1956,"margin":null}],"elections":[{"year":2026,"type":"General","date":"2026-11-03","total_votes":null,"result_status":null,"is_open_seat":null,"filing_deadline":"2026-06-02","forecast_rating":"Solid D","candidates":[]},{"year":2026,"type":"Primary_D","date":"2026-09-01","total_votes":null,"result_status":null,"is_open_seat":null,"filing_deadline":"2026-06-02","forecast_rating":null,"candidates":[]},{"year":2026,"type":"Primary_R","date":"2026-09-01","total_votes":null,"result_status":null,"is_open_seat":null,"filing_deadline":"2026-06-02","forecast_rating":null,"candidates":[]},{"year":2018,"type":"General","date":"2018-11-06","total_votes":null,"result_status":"Certified","is_open_seat":null,"filing_deadline":null,"forecast_rating":null,"candidates":[{"name":"Charlie Baker","party":"R","votes":null,"pct":null,"result":"Won","is_incumbent":false,"is_write_in":false,"election_type":"General","candidate_status":"Active","is_major":false}]},{"year":2014,"type":"General","date":"2014-11-04","total_votes":null,"result_status":"Certified","is_open_seat":null,"filing_deadline":null,"forecast_rating":null,"candidates":[{"name":"Charlie Baker","party":"R","votes":null,"pct":null,"result":"Won","is_incumbent":false,"is_write_in":false,"election_type":"General","candidate_status":"Active","is_major":false}]},{"year":2010,"type":"General","date":"2010-11-02","total_votes":null,"result_status":"Certified","is_open_seat":null,"filing_deadline":null,"forecast_rating":null,"candidates":[{"name":"Deval Patrick","party":"D","votes":null,"pct":null,"result":"Won","is_incumbent":false,"is_write_in":false,"election_type":"General","candidate_status":"Active","is_major":false}]},{"year":2006,"type":"General","date":"2006-11-07","total_votes":null,"result_status":"Certified","is_open_seat":null,"filing_deadline":null,"forecast_rating":null,"candidates":[{"name":"Deval Patrick","party":"D","votes":null,"pct":null,"result":"Won","is_incumbent":false,"is_write_in":false,"election_type":"General","candidate_status":"Active","is_major":false}]},{"year":2002,"type":"General","date":"2002-11-05","total_votes":null,"result_status":"Certified","is_open_seat":null,"filing_deadline":null,"forecast_rating":null,"candidates":[{"name":"Mitt Romney","party":"R","votes":null,"pct":null,"result":"Won","is_incumbent":false,"is_write_in":false,"election_type":"General","candidate_status":"Active","is_major":false}]},{"year":1998,"type":"General","date":"1998-11-03","total_votes":null,"result_status":"Certified","is_open_seat":null,"filing_deadline":null,"forecast_rating":null,"candidates":[{"name":"Paul Cellucci","party":"R","votes":null,"pct":null,"result":"Won","is_incumbent":false,"is_write_in":false,"election_type":"General","candidate_status":"Active","is_major":false}]},{"year":1994,"type":"General","date":"1994-11-08","total_votes":null,"result_status":"Certified","is_open_seat":null,"filing_deadline":null,"forecast_rating":null,"candidates":[{"name":"Bill Weld","party":"R","votes":null,"pct":null,"result":"Won","is_incumbent":false,"is_write_in":false,"election_type":"General","candidate_status":"Active","is_major":false}]},{"year":1990,"type":"General","date":"1990-11-06","total_votes":null,"result_status":"Certified","is_open_seat":null,"filing_deadline":null,"forecast_rating":null,"candidates":[{"name":"Bill Weld","party":"R","votes":null,"pct":null,"result":"Won","is_incumbent":false,"is_write_in":false,"election_type":"General","candidate_status":"Active","is_major":false}]},{"year":1986,"type":"General","date":"1986-11-04","total_votes":null,"result_status":"Certified","is_open_seat":null,"filing_deadline":null,"forecast_rating":null,"candidates":[{"name":"Michael Dukakis","party":"D","votes":null,"pct":null,"result":"Won","is_incumbent":false,"is_write_in":false,"election_type":"General","candidate_status":"Active","is_major":false}]},{"year":1982,"type":"General","date":"1982-11-02","total_votes":null,"result_status":"Certified","is_open_seat":null,"filing_deadline":null,"forecast_rating":null,"candidates":[{"name":"Michael Dukakis","party":"D","votes":null,"pct":null,"result":"Won","is_incumbent":false,"is_write_in":false,"election_type":"General","candidate_status":"Active","is_major":false}]},{"year":1978,"type":"General","date":"1978-11-07","total_votes":null,"result_status":"Certified","is_open_seat":null,"filing_deadline":null,"forecast_rating":null,"candidates":[{"name":"Edward J. King","party":"D","votes":null,"pct":null,"result":"Won","is_incumbent":false,"is_write_in":false,"election_type":"General","candidate_status":"Active","is_major":false}]},{"year":1974,"type":"General","date":"1974-11-05","total_votes":null,"result_status":"Certified","is_open_seat":null,"filing_deadline":null,"forecast_rating":null,"candidates":[{"name":"Michael Dukakis","party":"D","votes":null,"pct":null,"result":"Won","is_incumbent":false,"is_write_in":false,"election_type":"General","candidate_status":"Active","is_major":false}]},{"year":1970,"type":"General","date":"1970-11-03","total_votes":null,"result_status":"Certified","is_open_seat":null,"filing_deadline":null,"forecast_rating":null,"candidates":[{"name":"Francis Sargent","party":"R","votes":null,"pct":null,"result":"Won","is_incumbent":false,"is_write_in":false,"election_type":"General","candidate_status":"Active","is_major":false}]},{"year":1966,"type":"General","date":"1966-11-08","total_votes":null,"result_status":"Certified","is_open_seat":null,"filing_deadline":null,"forecast_rating":null,"candidates":[{"name":"John A. Volpe","party":"R","votes":null,"pct":null,"result":"Won","is_incumbent":false,"is_write_in":false,"election_type":"General","candidate_status":"Active","is_major":false}]},{"year":1964,"type":"General","date":"1964-11-03","total_votes":null,"result_status":"Certified","is_open_seat":null,"filing_deadline":null,"forecast_rating":null,"candidates":[{"name":"John A. Volpe","party":"R","votes":null,"pct":null,"result":"Won","is_incumbent":false,"is_write_in":false,"election_type":"General","candidate_status":"Active","is_major":false}]},{"year":1962,"type":"General","date":"1962-11-06","total_votes":null,"result_status":"Certified","is_open_seat":null,"filing_deadline":null,"forecast_rating":null,"candidates":[{"name":"Endicott Peabody","party":"D","votes":null,"pct":null,"result":"Won","is_incumbent":false,"is_write_in":false,"election_type":"General","candidate_status":"Active","is_major":false}]},{"year":1960,"type":"General","date":"1960-11-08","total_votes":null,"result_status":"Certified","is_open_seat":null,"filing_deadline":null,"forecast_rating":null,"candidates":[{"name":"John A. Volpe","party":"R","votes":null,"pct":null,"result":"Won","is_incumbent":false,"is_write_in":false,"election_type":"General","candidate_status":"Active","is_major":false}]},{"year":1958,"type":"General","date":"1958-11-04","total_votes":null,"result_status":"Certified","is_open_seat":null,"filing_deadline":null,"forecast_rating":null,"candidates":[{"name":"Foster Furcolo","party":"D","votes":null,"pct":null,"result":"Won","is_incumbent":false,"is_write_in":false,"election_type":"General","candidate_status":"Active","is_major":false}]},{"year":1956,"type":"General","date":"1956-11-06","total_votes":null,"result_status":"Certified","is_open_seat":null,"filing_deadline":null,"forecast_rating":null,"candidates":[{"name":"Foster Furcolo","party":"D","votes":null,"pct":null,"result":"Won","is_incumbent":false,"is_write_in":false,"election_type":"General","candidate_status":"Active","is_major":false}]}],"race_2026":{"is_open_seat":false,"forecast":"Solid D","forecast_cook":"Solid D","forecast_sabato":"Solid D","election_date":"2026-11-03","filing_deadline":"2026-06-02","primary_date":"2026-09-01","candidates":[]}}