{"generated_at":"2026-03-16T17:30:26.561569Z","state":"IN","state_name":"Indiana","office_type":"Attorney General","office_key":"ag","term_years":4,"term_limit":null,"method":"Elected","pres_2024_margin":"R+18.9","next_regular_election":2028,"current_holder":{"name":"Todd Rokita","party":"R","since":"2021-01-11","start_reason":"elected"},"timeline":[{"name":"Todd Rokita","party":"R","start":"2021-01-11","end":null,"start_reason":"elected","end_reason":null,"election_year":2020,"margin":16.6},{"name":"Curtis Hill","party":"R","start":"2017-01-01","end":"2021-01-01","start_reason":"elected","end_reason":"term_expired","election_year":2016,"margin":24.6},{"name":"Greg Zoeller","party":"R","start":"2009-01-01","end":"2017-01-01","start_reason":"elected","end_reason":"term_expired","election_year":2008,"margin":null},{"name":"Steve Carter","party":"R","start":"2001-01-01","end":"2009-01-01","start_reason":"elected","end_reason":"term_expired","election_year":2000,"margin":null},{"name":"Karen Freeman-Wilson","party":"D","start":"2000-01-01","end":"2001-01-01","start_reason":"elected","end_reason":"term_expired","election_year":2000,"margin":null},{"name":"Jeffrey A. Modisett","party":"D","start":"1997-01-01","end":"2000-01-01","start_reason":"elected","end_reason":"term_expired","election_year":1996,"margin":null},{"name":"Pamela Carter","party":"D","start":"1993-01-01","end":"1997-01-01","start_reason":"elected","end_reason":"term_expired","election_year":1992,"margin":null},{"name":"Linley E. Pearson","party":"R","start":"1981-01-01","end":"1993-01-01","start_reason":"elected","end_reason":"term_expired","election_year":1980,"margin":null},{"name":"Theodore L. Sendak","party":"R","start":"1969-01-01","end":"1981-01-01","start_reason":"elected","end_reason":"term_expired","election_year":1968,"margin":null},{"name":"John J. Dillon","party":"D","start":"1965-01-01","end":"1969-01-01","start_reason":"elected","end_reason":"term_expired","election_year":1964,"margin":null},{"name":"Edwin K. Steers","party":"R","start":"1953-01-01","end":"1965-01-01","start_reason":"elected","end_reason":"term_expired","election_year":null,"margin":null}],"elections":[{"year":2028,"type":"General","date":null,"total_votes":null,"result_status":null,"is_open_seat":null,"filing_deadline":null,"forecast_rating":null,"candidates":[{"candidate_id":105,"name":"Todd Rokita","party":"R","votes":null,"pct":null,"result":"Won","is_incumbent":false,"is_write_in":false,"election_type":"General","candidate_status":"Active","is_major":false}]},{"year":2024,"type":"General","date":null,"total_votes":null,"result_status":null,"is_open_seat":null,"filing_deadline":null,"forecast_rating":null,"candidates":[{"candidate_id":105,"name":"Todd Rokita","party":"R","votes":1669586,"pct":58.8,"result":"Won","is_incumbent":false,"is_write_in":false,"election_type":"General","candidate_status":"Active","is_major":false},{"candidate_id":75795,"name":"Destiny Scott Wells","party":"D","votes":1168512,"pct":41.2,"result":"Lost","is_incumbent":false,"is_write_in":false,"election_type":"General","candidate_status":"Active","is_major":false}]},{"year":2020,"type":"General","date":null,"total_votes":null,"result_status":null,"is_open_seat":null,"filing_deadline":null,"forecast_rating":null,"candidates":[{"candidate_id":105,"name":"Todd Rokita","party":"R","votes":1721995,"pct":58.3,"result":"Won","is_incumbent":false,"is_write_in":false,"election_type":"General","candidate_status":"Active","is_major":false},{"candidate_id":75976,"name":"Jonathan Weinzapfel","party":"D","votes":1229624,"pct":41.7,"result":"Lost","is_incumbent":false,"is_write_in":false,"election_type":"General","candidate_status":"Active","is_major":false}]},{"year":2016,"type":"General","date":null,"total_votes":null,"result_status":null,"is_open_seat":null,"filing_deadline":null,"forecast_rating":null,"candidates":[{"candidate_id":18164,"name":"Curtis Hill","party":"R","votes":1642623,"pct":62.3,"result":"Won","is_incumbent":false,"is_write_in":false,"election_type":"General","candidate_status":"Active","is_major":false},{"candidate_id":75896,"name":"Lorenzo Arredondo","party":"D","votes":993209,"pct":37.7,"result":"Lost","is_incumbent":false,"is_write_in":false,"election_type":"General","candidate_status":"Active","is_major":false}]},{"year":2012,"type":"General","date":null,"total_votes":null,"result_status":null,"is_open_seat":null,"filing_deadline":null,"forecast_rating":null,"candidates":[{"candidate_id":18163,"name":"Greg Zoeller","party":"R","votes":null,"pct":null,"result":"Won","is_incumbent":false,"is_write_in":false,"election_type":"General","candidate_status":"Active","is_major":false}]},{"year":2008,"type":"General","date":null,"total_votes":null,"result_status":null,"is_open_seat":null,"filing_deadline":null,"forecast_rating":null,"candidates":[{"candidate_id":18163,"name":"Greg Zoeller","party":"R","votes":null,"pct":null,"result":"Won","is_incumbent":false,"is_write_in":false,"election_type":"General","candidate_status":"Active","is_major":false}]},{"year":2004,"type":"General","date":null,"total_votes":null,"result_status":null,"is_open_seat":null,"filing_deadline":null,"forecast_rating":null,"candidates":[{"candidate_id":18162,"name":"Steve Carter","party":"R","votes":null,"pct":null,"result":"Won","is_incumbent":false,"is_write_in":false,"election_type":"General","candidate_status":"Active","is_major":false}]},{"year":2000,"type":"General","date":null,"total_votes":null,"result_status":null,"is_open_seat":null,"filing_deadline":null,"forecast_rating":null,"candidates":[{"candidate_id":18162,"name":"Steve Carter","party":"R","votes":null,"pct":null,"result":"Won","is_incumbent":false,"is_write_in":false,"election_type":"General","candidate_status":"Active","is_major":false}]},{"year":1996,"type":"General","date":null,"total_votes":null,"result_status":null,"is_open_seat":null,"filing_deadline":null,"forecast_rating":null,"candidates":[{"candidate_id":18160,"name":"Jeffrey A. Modisett","party":"D","votes":null,"pct":null,"result":"Won","is_incumbent":false,"is_write_in":false,"election_type":"General","candidate_status":"Active","is_major":false}],"flipped_seat":{"from":"R","to":"D"}},{"year":1992,"type":"General","date":null,"total_votes":null,"result_status":null,"is_open_seat":null,"filing_deadline":null,"forecast_rating":null,"candidates":[{"candidate_id":13642,"name":"Pamela Carter","party":"D","votes":null,"pct":null,"result":"Won","is_incumbent":false,"is_write_in":false,"election_type":"General","candidate_status":"Active","is_major":false}],"flipped_seat":{"from":"R","to":"D"}},{"year":1988,"type":"General","date":null,"total_votes":null,"result_status":null,"is_open_seat":null,"filing_deadline":null,"forecast_rating":null,"candidates":[{"candidate_id":18159,"name":"Linley E. Pearson","party":"R","votes":null,"pct":null,"result":"Won","is_incumbent":false,"is_write_in":false,"election_type":"General","candidate_status":"Active","is_major":false}]},{"year":1984,"type":"General","date":null,"total_votes":null,"result_status":null,"is_open_seat":null,"filing_deadline":null,"forecast_rating":null,"candidates":[{"candidate_id":18159,"name":"Linley E. Pearson","party":"R","votes":null,"pct":null,"result":"Won","is_incumbent":false,"is_write_in":false,"election_type":"General","candidate_status":"Active","is_major":false}]},{"year":1980,"type":"General","date":null,"total_votes":null,"result_status":null,"is_open_seat":null,"filing_deadline":null,"forecast_rating":null,"candidates":[{"candidate_id":18159,"name":"Linley E. Pearson","party":"R","votes":null,"pct":null,"result":"Won","is_incumbent":false,"is_write_in":false,"election_type":"General","candidate_status":"Active","is_major":false}]},{"year":1976,"type":"General","date":null,"total_votes":null,"result_status":null,"is_open_seat":null,"filing_deadline":null,"forecast_rating":null,"candidates":[{"candidate_id":18158,"name":"Theodore L. Sendak","party":"R","votes":null,"pct":null,"result":"Won","is_incumbent":false,"is_write_in":false,"election_type":"General","candidate_status":"Active","is_major":false}]},{"year":1972,"type":"General","date":null,"total_votes":null,"result_status":null,"is_open_seat":null,"filing_deadline":null,"forecast_rating":null,"candidates":[{"candidate_id":18158,"name":"Theodore L. Sendak","party":"R","votes":null,"pct":null,"result":"Won","is_incumbent":false,"is_write_in":false,"election_type":"General","candidate_status":"Active","is_major":false}]},{"year":1968,"type":"General","date":null,"total_votes":null,"result_status":null,"is_open_seat":null,"filing_deadline":null,"forecast_rating":null,"candidates":[{"candidate_id":18158,"name":"Theodore L. Sendak","party":"R","votes":null,"pct":null,"result":"Won","is_incumbent":false,"is_write_in":false,"election_type":"General","candidate_status":"Active","is_major":false}]},{"year":1964,"type":"General","date":null,"total_votes":null,"result_status":null,"is_open_seat":null,"filing_deadline":null,"forecast_rating":null,"candidates":[{"candidate_id":18157,"name":"John J. Dillon","party":"D","votes":null,"pct":null,"result":"Won","is_incumbent":false,"is_write_in":false,"election_type":"General","candidate_status":"Active","is_major":false}],"flipped_seat":{"from":"R","to":"D"}},{"year":1960,"type":"General","date":null,"total_votes":null,"result_status":null,"is_open_seat":null,"filing_deadline":null,"forecast_rating":null,"candidates":[{"candidate_id":18156,"name":"Edwin K. Steers","party":"R","votes":null,"pct":null,"result":"Won","is_incumbent":false,"is_write_in":false,"election_type":"General","candidate_status":"Active","is_major":false}]}],"race_2026":null}